poetry_plugin_lambda_build_v2/__init__.py
poetry_plugin_lambda_build_v2/commands.py
poetry_plugin_lambda_build_v2/docker.py
poetry_plugin_lambda_build_v2/parameters.py
poetry_plugin_lambda_build_v2/plugin.py
poetry_plugin_lambda_build_v2/recipes.py
poetry_plugin_lambda_build_v2/requirements.py
poetry_plugin_lambda_build_v2/utils.py
poetry_plugin_lambda_build_v2/walker.py
poetry_plugin_lambda_build_v2/zip.py
poetry_plugin_lambda_build_v2-2.0.0.dist-info/LICENSE
poetry_plugin_lambda_build_v2-2.0.0.dist-info/METADATA
poetry_plugin_lambda_build_v2-2.0.0.dist-info/WHEEL
poetry_plugin_lambda_build_v2-2.0.0.dist-info/entry_points.txt
poetry_plugin_lambda_build_v2-2.0.0.dist-info/RECORD
