Metadata-Version: 2.3
Name: poetry-plugin-lambda-build-v2
Version: 2.0.0
Summary: The plugin for poetry that allows you to build zip packages suited for serverless deployment like AWS Lambda, Google App Engine, Azure App Service, and more...
Author: Michal Murawski
Author-email: mmurawski777@gmail.com
Requires-Python: ==3.13.1
Classifier: Programming Language :: Python :: 3
Requires-Dist: docker (==7.1.0)
